{
    "id": "L0-N0|L1-N0|L2-N1",
    "state": 0,
    "n_failed_generations": 0,
    "partial_formulation_up_until_now": "\n\n# -- Objects --\n\n\n```python\nfrom typing import Annotated\nfrom pydantic import Field\n\n# Define object types for items and positions\nItem = DSRecord({\n    \"width\": Annotated[int, Field(strict=True, ge=1, le=5)],\n    \"height\": Annotated[int, Field(strict=True, ge=1, le=9)]\n})\n\nPosition = DSRecord({\n    \"x\": Annotated[int, Field(strict=True, ge=0, le=1000)],\n    \"y\": Annotated[int, Field(strict=True, ge=0, le=1000)]\n})\n```\n\n\n\n# --- Constants ---\nBOX_HEIGHT : Annotated[int, Field(strict=True, ge=1, le=12)] = 12\nBOX_WIDTH : Annotated[int, Field(strict=True, ge=1, le=5)] = 5\nITEM1 : Item = {\"width\": 3, \"height\": 4}\nITEM2 : Item = {\"width\": 1, \"height\": 2}\nITEM3 : Item = {\"width\": 5, \"height\": 4}\nITEM4 : Item = {\"width\": 2, \"height\": 4}\nITEM5 : Item = {\"width\": 1, \"height\": 3}\nITEM6 : Item = {\"width\": 5, \"height\": 9}\nITEM7 : Item = {\"width\": 5, \"height\": 3}\nITEM8 : Item = {\"width\": 5, \"height\": 1}\nITEMS : Annotated[list[Item], Len(8, 8)] = [ITEM1, ITEM2, ITEM3, ITEM4, ITEM5, ITEM6, ITEM7, ITEM8]\nN_ITEMS : int = 8\nnr_used_boxes : Annotated[int, Field(strict=True, ge=0, le=8)]\nitem_box_assignments : Annotated[list[int], Len(8, 8)]\nx_y_positions : Annotated[list[Position], Len(8, 8)]\nN_ITEMS : int = 8\nN_ITEM_BOX_ASSIGNMENTS : int = 8\nN_X_Y_POSITIONS : int = 8\n",
    "objective_val": null,
    "solution_model": null,
    "solve_time": null
}